COPYING.txt
MANIFEST.in
README.md
package_variables.py
requirements.txt
setup.py
mesma/__init__.py
mesma/mesma_plugin.py
mesma.egg-info/PKG-INFO
mesma.egg-info/SOURCES.txt
mesma.egg-info/dependency_links.txt
mesma.egg-info/entry_points.txt
mesma.egg-info/top_level.txt
mesma/core/__init__.py
mesma/core/hard_classification.py
mesma/core/mesma.py
mesma/core/shade_normalisation.py
mesma/hubdc/__init__.py
mesma/hubdc/applier.py
mesma/hubdc/core.py
mesma/hubdc/hubdcerrors.py
mesma/hubdc/progressbar.py
mesma/hubdc/writer.py
mesma/images/histogram.png
mesma/images/mesma-vis.png
mesma/images/mesma.png
mesma/images/shade.png
mesma/interfaces/__init__.py
mesma/interfaces/complexityWidget.ui
mesma/interfaces/hard_classification.ui
mesma/interfaces/hard_classification_cli.py
mesma/interfaces/hard_classification_gui.py
mesma/interfaces/imports.py
mesma/interfaces/mesma.ui
mesma/interfaces/mesmaModels.ui
mesma/interfaces/mesma_cli.py
mesma/interfaces/mesma_gui.py
mesma/interfaces/mesma_visualisation.ui
mesma/interfaces/mesma_visualisation_gui.py
mesma/interfaces/operators.py
mesma/interfaces/shade_normalisation.ui
mesma/interfaces/shade_normalisation_cli.py
mesma/interfaces/shade_normalisation_gui.py
mesma/qps/__init__.py
mesma/qps/cursorlocationvalue.py
mesma/qps/layerproperties.py
mesma/qps/maptools.py
mesma/qps/models.py
mesma/qps/qgisclasses.py
mesma/qps/resources.py
mesma/qps/searchfiledialog.py
mesma/qps/setup.py
mesma/qps/subdatasets.py
mesma/qps/testing.py
mesma/qps/unitmodel.py
mesma/qps/utils.py
mesma/qps/vectorlayertools.py
mesma/qps/classification/__init__.py
mesma/qps/classification/classificationscheme.py
mesma/qps/classification/classificationscheme.ui
mesma/qps/crosshair/__init__.py
mesma/qps/crosshair/crosshair.py
mesma/qps/crosshair/crosshairwidget.ui
mesma/qps/layerconfigwidgets/__init__.py
mesma/qps/layerconfigwidgets/core.py
mesma/qps/layerconfigwidgets/gdalmetadata.py
mesma/qps/layerconfigwidgets/rasterbands.py
mesma/qps/layerconfigwidgets/vectorlabeling.py
mesma/qps/layerconfigwidgets/vectorlayerfields.py
mesma/qps/make/__init__.py
mesma/qps/make/deploy.py
mesma/qps/make/make.py
