Metadata-Version: 2.1
Name: mesma
Version: 1.0.8
Summary: MESMA (Multiple Endmember Spectral Mixture Analysis) is a common unmixing technique in the fieldof remote sensing. This suite of processing tools allows you to unmix your image with MESMA (with multi-level fusion, stable zone unmixing, ...) and post-process the MESMA results (visualisation tool, shade normalisation, soft to hard classification).
Home-page: https://bitbucket.org/kul-reseco/mesma
Author: Ann Crabbé
Author-email: acrabbe.foss@gmail.com
License: UNKNOWN
Project-URL: Documentation, https://mesma.readthedocs.io
Project-URL: Source Code, https://bitbucket.org/kul-reseco/mesma/src
Project-URL: Issue Tracker, https://bitbucket.org/kul-reseco/mesma/issues
Keywords: sma,mesma,szu,remote sensing,viper,spectral mixture analysis
Platform: UNKNOWN
